{
    "docker_registry": "ghcr.io/sieve-project/action",
    "namespace": "default",
    "leading_api": "kind-control-plane",
    "following_api": "kind-control-plane3",
    "state_update_summary_check_enabled": true,
    "end_state_check_enabled": true,
    "workload_error_check_enabled": true,
    "controller_exception_check_enabled": true,
    "state_update_summary_check_event_list": [
        "DELETED",
        "ADDED"
    ],
    "end_state_resource_check_list": [
        "pod",
        "deployment",
        "statefulset",
        "persistentvolumeclaim",
        "secret",
        "service",
        "replicaset"
    ],
    "compress_trivial_reconcile_enabled": false,
    "workload_hard_timeout": 600,
    "workload_soft_timeout": 100,
    "generate_debugging_information_enabled": true,
    "causality_prunning_enabled": true,
    "effective_updates_pruning_enabled": true,
    "nondeterministic_pruning_enabled": true,
    "persist_test_plans_enabled": true
}